distrand/__init__.py
distrand/distrand.py
distrand-0.1.2.dist-info/licenses/LICENSE
distrand-0.1.2.dist-info/METADATA
distrand-0.1.2.dist-info/WHEEL
distrand-0.1.2.dist-info/top_level.txt
distrand-0.1.2.dist-info/RECORD
