Metadata-Version: 2.4
Name: distrand
Version: 0.1.2
Summary: Generate spaced random numbers with minimum distance constraints.
Author: Syed Mohammad Talha Husain
License-Expression: Apache-2.0
Project-URL: Homepage, https://github.com/Eggman5800/distrand/
Project-URL: Issues, https://github.com/Eggman5800/distrand/issues
Keywords: random,sampling,spacing,numpy,utility
Classifier: Programming Language :: Python :: 3
Classifier: Programming Language :: Python :: 3.7
Classifier: Intended Audience :: Developers
Classifier: Topic :: Scientific/Engineering :: Mathematics
Classifier: Operating System :: OS Independent
Requires-Python: >=3.7
License-File: LICENSE
Requires-Dist: numpy>=1.20
Dynamic: license-file
